Workbook

Sheet Инструкция
B1: Финансовая модель Python Method Center — «Реабилитация без границ»
B3: Как пользоваться:
B4: • ЖЁЛТЫЕ ячейки на листе «Вводные» — заполните вашими реальными цифрами. Всё остальное пересчитается само.
B5: • Синий шрифт = вводные значения (можно менять). Чёрный = формулы (не трогать). Зелёный = ссылки на другой лист.
B6: • Все суммы в долларах США (USD), без НДС.
B8: Источники данных:
B9: • 480 кейсов за 24 месяца, действующая корпорация, 2 года налоговой отчётности — со слов основателя (Анна, 23.07.2026).
B10: • Стоимость инфраструктуры и ИИ — фактические тарифы Vercel/Supabase/Anthropic/OpenAI, июль 2026.
B11: • Цены — факт от 23.07.2026: «5 недель» $1200 (+5% сбор, +$180 доставка формулы-подарка) = $1440; «100 дней» $3500 (+5% сбор) = $3675.
B12: • Жёлтым остались: доля «100 дней», продления, рост, себестоимость подарка, зарплаты, маркетинг, раунд — заполните.
B14: Листы:
B15: • «Вводные» — все предположения модели.
... B18: • «Сценарии» — консервативный / базовый / агрессивный рост.

Sheet Вводные
A1: Вводные и предположения
A3: ИСТОРИЯ (факт)
A4: Кейсов за последние 24 месяца (до платформы) | B4: 480 | C4: Факт: работа Карена через Telegram/WhatsApp, оплаты на корпорацию. Со слов основателя.
A5: Новых клиентов в месяц на старте платформы | B5: =B4/24 -> 20 | C5: Исторический темп: 480 за 24 мес = 20 в месяц. Формула.
A7: ЦЕНЫ (заполнить реальными!)
A8: Цена тарифа «5 недель», $ | B8: 1200 | C8: ФАКТ — установлено основателем 23.07.2026.
A9: Цена тарифа «100 дней», $ | B9: 3500 | C9: ФАКТ — установлено основателем 23.07.2026.
A10: Сервисный сбор, % к каждому тарифу | B10: 0.05 | C10: ФАКТ — 5% добавляется к сумме тарифа.
A11: Доставка формулы (тариф «5 недель»), $ | B11: 180 | C11: ФАКТ — формула отправляется Кареном в подарок, клиент оплачивает доставку $180.
A12: Себестоимость формулы и доставки, $ | B12: 120 | C12: ПРЕДПОЛОЖЕНИЕ — во сколько центру обходится формула + отправка. Замените фактом.
A13: Доля клиентов, выбирающих «100 дней» | B13: 0.4 | C13: ПРЕДПОЛОЖЕНИЕ — оцените по вашим 480 кейсам.
A14: Средний чек (с сбором и доставкой), $ | B14: =(B8*(1+B10)+B11)*(1-B13)+B9*(1+B10)*B13 -> 2334 | C14: 5 недель: $1200×1,05+$180=$1440; 100 дней: $3500×1,05=$3675. Средневзвешенно. Формула.
A15: Доля клиентов, продлевающих сопровождение | B15: 0.2 | C15: ПРЕДПОЛОЖЕНИЕ — доля повторных покупок после завершения тарифа.
A17: РОСТ
A18: Рост новых клиентов, % в месяц (базовый сценарий) | B18: 0.08 | C18: Базовый: +8% в месяц. Сценарии — на листе «Сценарии».
A20: ЗАТРАТЫ
A21: Эквайринг Stripe, % от выручки | B21: 0.032 | C21: 2,9% + $0,30 за транзакцию ≈ 3,2% при среднем чеке. Тариф Stripe US, июль 2026.
A22: ИИ-затраты на активного клиента в месяц, $ | B22: 1 | C22: Оценка из фактических тарифов Claude/GPT при текущем режиме «Лучший ответ».
A23: Инфраструктура (Vercel, Supabase Pro, домен), $/мес | B23: 130 | C23: Факт: Supabase Pro $25 + Vercel Pro ~$20 + резерв. Фиксированные.
A24: Команда (Карен, Анна, поддержка), $/мес — год 1 | B24: 8000 | C24: ПРЕДПОЛОЖЕНИЕ — суммарные выплаты команде. Замените реальными.
A25: Рост затрат на команду в год 2 (множитель) | B25: 1.5 | C25: ПРЕДПОЛОЖЕНИЕ: расширение команды на 2-м году.
A26: Маркетинг, % от выручки | B26: 0.15 | C26: ПРЕДПОЛОЖЕНИЕ — бюджет привлечения.
A27: Юристы, бухгалтерия, прочее, $/мес | B27: 500 | C27: ПРЕДПОЛОЖЕНИЕ.
A29: ИНВЕСТИЦИИ И ПРИВЛЕЧЕНИЕ
A30: Запрашиваемый раунд, $ | B30: 150000 | C30: ПРЕДПОЛОЖЕНИЕ — сумма, которую вы просите у инвестора.
A31: Стоимость привлечения клиента (CAC), $ | B31: 60 | C31: ПРЕДПОЛОЖЕНИЕ = маркетинг на клиента. Проверится фактом первых месяцев.

Sheet Прогноз 24 мес
A1: Помесячный прогноз (базовый сценарий)
A2: Показатель | B2: М1 | C2: М2 | D2: М3 | E2: М4 | F2: М5 | G2: М6 | H2: М7 | I2: М8 | J2: М9 | K2: М10 | L2: М11 | M2: М12 | N2: М13 | O2: М14 | P2: М15 | Q2: М16 | R2: М17 | S2: М18 | T2: М19 | U2: М20 | V2: М21 | W2: М22 | X2: М23 | Y2: М24
A3: Новые клиенты | B3: =Вводные!$B$5 -> 20 | C3: =ROUND(B3*(1+Вводные!$B$18),1) -> 21.6 | D3: =ROUND(C3*(1+Вводные!$B$18),1) -> 23.3 | E3: =ROUND(D3*(1+Вводные!$B$18),1) -> 25.2 | F3: =ROUND(E3*(1+Вводные!$B$18),1) -> 27.2 | G3: =ROUND(F3*(1+Вводные!$B$18),1) -> 29.4 | H3: =ROUND(G3*(1+Вводные!$B$18),1) -> 31.8 | I3: =ROUND(H3*(1+Вводные!$B$18),1) -> 34.3 | J3: =ROUND(I3*(1+Вводные!$B$18),1) -> 37 | ... Y3: =ROUND(X3*(1+Вводные!$B$18),1) -> 117.6
A4: Продажи «5 недель», шт | B4: =B3*(1-Вводные!$B$13) -> 12 | C4: =C3*(1-Вводные!$B$13) -> 12.96 | D4: =D3*(1-Вводные!$B$13) -> 13.98 | E4: =E3*(1-Вводные!$B$13) -> 15.12 | F4: =F3*(1-Вводные!$B$13) -> 16.32 | G4: =G3*(1-Вводные!$B$13) -> 17.64 | H4: =H3*(1-Вводные!$B$13) -> 19.08 | I4: =I3*(1-Вводные!$B$13) -> 20.58 | ... Y4: =Y3*(1-Вводные!$B$13) -> 70.56
A5: Продажи «100 дней», шт | B5: =B3*Вводные!$B$13 -> 8 | C5: =C3*Вводные!$B$13 -> 8.64 | D5: =D3*Вводные!$B$13 -> 9.32 | E5: =E3*Вводные!$B$13 -> 10.08 | F5: =F3*Вводные!$B$13 -> 10.88 | G5: =G3*Вводные!$B$13 -> 11.76 | H5: =H3*Вводные!$B$13 -> 12.72 | I5: =I3*Вводные!$B$13 -> 13.72 | ... Y5: =Y3*Вводные!$B$13 -> 47.04
A6: Продления, шт | B6: 0 | C6: 0 | D6: =B3*Вводные!$B$15 -> 4 | E6: =C3*Вводные!$B$15 -> 4.32 | F6: =D3*Вводные!$B$15 -> 4.66 | G6: =E3*Вводные!$B$15 -> 5.04 | H6: =F3*Вводные!$B$15 -> 5.44 | I6: =G3*Вводные!$B$15 -> 5.88 | J6: =H3*Вводные!$B$15 -> 6.36 | K6: =I3*Вводные!$B$15 -> 6.86 | ... Y6: =W3*Вводные!$B$15 -> 20.16
A7: Выручка новые, $ | B7: =B4*(Вводные!$B$8*(1+Вводные!$B$10)+Вводные!$B$11)+B5*Вводные!$B$9*(1+Вводные!$B$10) -> 46680 | C7: =C4*(Вводные!$B$8*(1+Вводные!$B$10)+Вводные!$B$11)+C5*Вводные!$B$9*(1+Вводные!$B$10) -> 50414.4 | D7: =D4*(Вводные!$B$8*(1+Вводные!$B$10)+Вводные!$B$11)+D5*Вводные!$B$9*(1+Вводные!$B$10) -> 54382.2 | E7: =E4*(Вводные!$B$8*(1+Вводные!$B$10)+Вводные!$B$11)+E5*Вводные!$B$9*(1+Вводные!$B$10) -> 58816.8 | F7: =F4*(Вводные!$B$8*(1+Вводные!$B$10)+Вводные!$B$11)+F5*Вводные!$B$9*(1+Вводные!$B$10) -> 63484.8 | G7: =G4*(Вводные!$B$8*(1+Вводные!$B$10)+Вводные!$B$11)+G5*Вводные!$B$9*(1+Вводные!$B$10) -> 68619.6 | H7: =H4*(Вводные!$B$8*(1+Вводные!$B$10)+Вводные!$B$11)+H5*Вводные!$B$9*(1+Вводные!$B$10) -> 74221.2 | I7: =I4*(Вводные!$B$8*(1+Вводные!$B$10)+Вводные!$B$11)+I5*Вводные!$B$9*(1+Вводные!$B$10) -> 80056.2 | ... Y7: =Y4*(Вводные!$B$8*(1+Вводные!$B$10)+Вводные!$B$11)+Y5*Вводные!$B$9*(1+Вводные!$B$10) -> 274478.4
A8: Выручка продления, $ | B8: =B6*Вводные!$B$14 -> 0 | C8: =C6*Вводные!$B$14 -> 0 | D8: =D6*Вводные!$B$14 -> 9336 | E8: =E6*Вводные!$B$14 -> 10082.88 | F8: =F6*Вводные!$B$14 -> 10876.44 | G8: =G6*Вводные!$B$14 -> 11763.36 | H8: =H6*Вводные!$B$14 -> 12696.96 | I8: =I6*Вводные!$B$14 -> 13723.92 | ... Y8: =Y6*Вводные!$B$14 -> 47053.44
A9: ВЫРУЧКА ИТОГО, $ | B9: =B7+B8 -> 46680 | C9: =C7+C8 -> 50414.4 | D9: =D7+D8 -> 63718.2 | E9: =E7+E8 -> 68899.68 | F9: =F7+F8 -> 74361.24 | G9: =G7+G8 -> 80382.96 | H9: =H7+H8 -> 86918.16 | I9: =I7+I8 -> 93780.12 | ... Y9: =Y7+Y8 -> 321531.84
A10: Активные клиенты (оценка) | B10: =B3 -> 20 | C10: =C3+B3 -> 41.6 | D10: =D3+C3+B3 -> 64.9 | E10: =E3+D3+C3 -> 70.1 | F10: =F3+E3+D3 -> 75.7 | G10: =G3+F3+E3 -> 81.8 | H10: =H3+G3+F3 -> 88.4 | I10: =I3+H3+G3 -> 95.5 | J10: =J3+I3+H3 -> 103.1 | K10: =K3+J3+I3 -> 111.3 | ... Y10: =Y3+X3+W3 -> 327.3
A11: Эквайринг, $ | B11: =B9*Вводные!$B$21 -> 1493.76 | C11: =C9*Вводные!$B$21 -> 1613.2608 | D11: =D9*Вводные!$B$21 -> 2038.9824 | E11: =E9*Вводные!$B$21 -> 2204.7898 | F11: =F9*Вводные!$B$21 -> 2379.5597 | G11: =G9*Вводные!$B$21 -> 2572.2547 | H11: =H9*Вводные!$B$21 -> 2781.3811 | I11: =I9*Вводные!$B$21 -> 3000.9638 | ... Y11: =Y9*Вводные!$B$21 -> 10289.019
A12: ИИ-затраты, $ | B12: =B10*Вводные!$B$22 -> 20 | C12: =C10*Вводные!$B$22 -> 41.6 | D12: =D10*Вводные!$B$22 -> 64.9 | E12: =E10*Вводные!$B$22 -> 70.1 | F12: =F10*Вводные!$B$22 -> 75.7 | G12: =G10*Вводные!$B$22 -> 81.8 | H12: =H10*Вводные!$B$22 -> 88.4 | I12: =I10*Вводные!$B$22 -> 95.5 | ... Y12: =Y10*Вводные!$B$22 -> 327.3
A13: ВАЛОВАЯ ПРИБЫЛЬ, $ | B13: =B9-B11-B12-B4*Вводные!$B$12 -> 43726.24 | C13: =C9-C11-C12-C4*Вводные!$B$12 -> 47204.339 | D13: =D9-D11-D12-D4*Вводные!$B$12 -> 59936.718 | E13: =E9-E11-E12-E4*Вводные!$B$12 -> 64810.39 | F13: =F9-F11-F12-F4*Вводные!$B$12 -> 69947.58 | G13: =G9-G11-G12-G4*Вводные!$B$12 -> 75612.105 | H13: =H9-H11-H12-H4*Вводные!$B$12 -> 81758.779 | I13: =I9-I11-I12-I4*Вводные!$B$12 -> 88214.056 | ... Y13: =Y9-Y11-Y12-Y4*Вводные!$B$12 -> 302448.32
A14: Команда, $ | B14: =IF(1>12,Вводные!$B$24*Вводные!$B$25,Вводные!$B$24) -> 8000 | C14: =IF(2>12,Вводные!$B$24*Вводные!$B$25,Вводные!$B$24) -> 8000 | D14: =IF(3>12,Вводные!$B$24*Вводные!$B$25,Вводные!$B$24) -> 8000 | E14: =IF(4>12,Вводные!$B$24*Вводные!$B$25,Вводные!$B$24) -> 8000 | F14: =IF(5>12,Вводные!$B$24*Вводные!$B$25,Вводные!$B$24) -> 8000 | G14: =IF(6>12,Вводные!$B$24*Вводные!$B$25,Вводные!$B$24) -> 8000 | H14: =IF(7>12,Вводные!$B$24*Вводные!$B$25,Вводные!$B$24) -> 8000 | I14: =IF(8>12,Вводные!$B$24*Вводные!$B$25,Вводные!$B$24) -> 8000 | J14: =IF(9>12,Вводные!$B$24*Вводные!$B$25,Вводные!$B$24) -> 8000 | K14: =IF(10>12,Вводные!$B$24*Вводные!$B$25,Вводные!$B$24) -> 8000 | L14: =IF(11>12,Вводные!$B$24*Вводные!$B$25,Вводные!$B$24) -> 8000 | M14: =IF(12>12,Вводные!$B$24*Вводные!$B$25,Вводные!$B$24) -> 8000 | N14: =IF(13>12,Вводные!$B$24*Вводные!$B$25,Вводные!$B$24) -> 12000 | O14: =IF(14>12,Вводные!$B$24*Вводные!$B$25,Вводные!$B$24) -> 12000 | P14: =IF(15>12,Вводные!$B$24*Вводные!$B$25,Вводные!$B$24) -> 12000 | Q14: =IF(16>12,Вводные!$B$24*Вводные!$B$25,Вводные!$B$24) -> 12000 | R14: =IF(17>12,Вводные!$B$24*Вводные!$B$25,Вводные!$B$24) -> 12000 | S14: =IF(18>12,Вводные!$B$24*Вводные!$B$25,Вводные!$B$24) -> 12000 | T14: =IF(19>12,Вводные!$B$24*Вводные!$B$25,Вводные!$B$24) -> 12000 | U14: =IF(20>12,Вводные!$B$24*Вводные!$B$25,Вводные!$B$24) -> 12000 | V14: =IF(21>12,Вводные!$B$24*Вводные!$B$25,Вводные!$B$24) -> 12000 | W14: =IF(22>12,Вводные!$B$24*Вводные!$B$25,Вводные!$B$24) -> 12000 | X14: =IF(23>12,Вводные!$B$24*Вводные!$B$25,Вводные!$B$24) -> 12000 | Y14: =IF(24>12,Вводные!$B$24*Вводные!$B$25,Вводные!$B$24) -> 12000
A15: Маркетинг, $ | B15: =B9*Вводные!$B$26 -> 7002 | C15: =C9*Вводные!$B$26 -> 7562.16 | D15: =D9*Вводные!$B$26 -> 9557.73 | E15: =E9*Вводные!$B$26 -> 10334.952 | F15: =F9*Вводные!$B$26 -> 11154.186 | G15: =G9*Вводные!$B$26 -> 12057.444 | H15: =H9*Вводные!$B$26 -> 13037.724 | I15: =I9*Вводные!$B$26 -> 14067.018 | ... Y15: =Y9*Вводные!$B$26 -> 48229.776
A16: Инфраструктура и прочее, $ | B16: =Вводные!$B$23+Вводные!$B$27 -> 630 | C16: =Вводные!$B$23+Вводные!$B$27 -> 630 | D16: =Вводные!$B$23+Вводные!$B$27 -> 630 | E16: =Вводные!$B$23+Вводные!$B$27 -> 630 | F16: =Вводные!$B$23+Вводные!$B$27 -> 630 | G16: =Вводные!$B$23+Вводные!$B$27 -> 630 | H16: =Вводные!$B$23+Вводные!$B$27 -> 630 | I16: =Вводные!$B$23+Вводные!$B$27 -> 630 | ... Y16: =Вводные!$B$23+Вводные!$B$27 -> 630
A17: EBITDA, $ | B17: =B13-B14-B15-B16 -> 28094.24 | C17: =C13-C14-C15-C16 -> 31012.179 | D17: =D13-D14-D15-D16 -> 41748.988 | E17: =E13-E14-E15-E16 -> 45845.438 | F17: =F13-F14-F15-F16 -> 50163.394 | G17: =G13-G14-G15-G16 -> 54924.661 | H17: =H13-H14-H15-H16 -> 60091.055 | I17: =I13-I14-I15-I16 -> 65517.038 | ... Y17: =Y13-Y14-Y15-Y16 -> 241588.55
A18: Денежная позиция (раунд + накопл. EBITDA), $ | B18: =Вводные!$B$30+B17 -> 178094.24 | C18: =B18+C17 -> 209106.42 | D18: =C18+D17 -> 250855.41 | E18: =D18+E17 -> 296700.85 | F18: =E18+F17 -> 346864.24 | G18: =F18+G17 -> 401788.9 | H18: =G18+H17 -> 461879.96 | I18: =H18+I17 -> 527396.99 | J18: =I18+J17 -> 598783.33 | ... Y18: =X18+Y17 -> 2770493.5
A20: Активные клиенты ≈ сумма новых за последние 3 месяца (средняя длительность сопровождения ~10 недель). Продления учитываются со сдвигом в 2 месяца.

Sheet Годовые итоги
A1: Годовые итоги и юнит-экономика
A2: Показатель | B2: Год 1 | C2: Год 2
A3: Выручка, $ | B3: =SUM('Прогноз 24 мес'!B9:M9) -> 1021498.4 | C3: =SUM('Прогноз 24 мес'!N9:Y9) -> 2616040.6
A4: Валовая прибыль, $ | B4: =SUM('Прогноз 24 мес'!B13:M13) -> 960469.59 | C4: =SUM('Прогноз 24 мес'!N13:Y13) -> 2460774.8
A5: Валовая маржа, % | B5: =B4/B3 -> 0.94025556 | C5: =C4/C3 -> 0.94064855
A6: EBITDA, $ | B6: =SUM('Прогноз 24 мес'!B17:M17) -> 703684.82 | C6: =SUM('Прогноз 24 мес'!N17:Y17) -> 1916808.7
A7: EBITDA-маржа, % | B7: =B6/B3 -> 0.68887508 | C7: =C6/C3 -> 0.73271367
A8: Новых клиентов за год | B8: =SUM('Прогноз 24 мес'!B3:M3) -> 379.7 | C8: =SUM('Прогноз 24 мес'!N3:Y3) -> 956.8
A9: Денежная позиция на конец года, $ | B9: ='Прогноз 24 мес'!M18 -> 853684.82 | C9: ='Прогноз 24 мес'!Y18 -> 2770493.5
A11: ЮНИТ-ЭКОНОМИКА (на одного клиента)
A12: Средний чек, $ | B12: =Вводные!B14 -> 2334
A13: LTV (чек × (1 + доля продлений)), $ | B13: =Вводные!B14*(1+Вводные!B15) -> 2800.8
A14: CAC, $ | B14: =Вводные!B31 -> 60
A15: LTV / CAC | B15: =B13/B14 -> 46.68
A16: Переменные затраты на клиента (эквайринг + ИИ + подарок), $ | B16: =Вводные!B14*Вводные!B21+Вводные!B22*3+(1-Вводные!B13)*Вводные!B12 -> 149.688
A17: Валовая прибыль на клиента, $ | B17: =B12-B16 -> 2184.312

Sheet Сценарии
A1: Сценарии роста (2 года)
A2: Показатель | B2: Консервативный | C2: Базовый | D2: Агрессивный
A3: Рост новых клиентов, % в месяц | B3: 0.04 | C3: =Вводные!B18 -> 0.08 | D3: 0.12
A4: Новых клиентов за 24 мес | B4: =Вводные!$B$5*(((1+B3)^24)-1)/B3 -> 781.65208 | C4: =Вводные!$B$5*(((1+C3)^24)-1)/C3 -> 1335.2952 | D4: =Вводные!$B$5*(((1+D3)^24)-1)/D3 -> 2363.1048
A5: Выручка за 24 мес (с продлениями), $ | B5: =B4*Вводные!$B$14*(1+Вводные!$B$15) -> 2189251.2 | C5: =C4*Вводные!$B$14*(1+Вводные!$B$15) -> 3739894.8 | D5: =D4*Вводные!$B$14*(1+Вводные!$B$15) -> 6618584
A6: Средняя выручка в месяц к концу 2-го года, $ | B6: =Вводные!$B$5*((1+B3)^23)*Вводные!$B$14*(1+Вводные!$B$15) -> 138063.51 | C6: =Вводные!$B$5*((1+C3)^23)*Вводные!$B$14*(1+Вводные!$B$15) -> 328895.91 | D6: =Вводные!$B$5*((1+D3)^23)*Вводные!$B$14*(1+Вводные!$B$15) -> 759148.28
A8: Сценарии считаются по упрощённой формуле геометрического роста; базовый сценарий детально расписан на листе «Прогноз 24 мес».
